{
  "tracker_name": "particle-NCVmm-125N-10q-0.01al-0.1dsig-16nbins",
  "results": [
    {
      "sequence_name": "ball",
      "sequence_length": 602,
      "overlap": 0.6068128562116654,
      "failures": 0,
      "speed": 61.43883798378389,
      "init_speed": 1291.3223140495868
    },
    {
      "sequence_name": "basketball",
      "sequence_length": 725,
      "overlap": 0.6429603983755618,
      "failures": 1,
      "speed": 46.650608892999756,
      "init_speed": 1226.2415695892091
    },
    {
      "sequence_name": "bicycle",
      "sequence_length": 271,
      "overlap": 0.388552429256842,
      "failures": 0,
      "speed": 67.58247992787875,
      "init_speed": 1763.3574325515783
    },
    {
      "sequence_name": "bolt",
      "sequence_length": 350,
      "overlap": 0.527847437705551,
      "failures": 4,
      "speed": 53.27045760614974,
      "init_speed": 1644.5745485642865
    },
    {
      "sequence_name": "car",
      "sequence_length": 252,
      "overlap": 0.35158759653381433,
      "failures": 0,
      "speed": 62.57922666677657,
      "init_speed": 1428.1633818908883
    },
    {
      "sequence_name": "david",
      "sequence_length": 770,
      "overlap": 0.5376088504156785,
      "failures": 4,
      "speed": 44.4673171323013,
      "init_speed": 1506.7956483741673
    },
    {
      "sequence_name": "diving",
      "sequence_length": 219,
      "overlap": 0.3253427508753097,
      "failures": 1,
      "speed": 47.891265904314224,
      "init_speed": 1425.3135689851767
    },
    {
      "sequence_name": "drunk",
      "sequence_length": 1210,
      "overlap": 0.34715235119104465,
      "failures": 0,
      "speed": 37.700857628456674,
      "init_speed": 1279.9180852425445
    },
    {
      "sequence_name": "fernando",
      "sequence_length": 292,
      "overlap": 0.3565506713160065,
      "failures": 1,
      "speed": 13.495771155761005,
      "init_speed": 842.6729586247577
    },
    {
      "sequence_name": "fish1",
      "sequence_length": 436,
      "overlap": 0.24903119930242137,
      "failures": 2,
      "speed": 67.1784545260644,
      "init_speed": 1804.1857108491702
    },
    {
      "sequence_name": "fish2",
      "sequence_length": 310,
      "overlap": 0.39982036120897607,
      "failures": 5,
      "speed": 49.77884008880612,
      "init_speed": 1657.6600470775454
    },
    {
      "sequence_name": "gymnastics",
      "sequence_length": 207,
      "overlap": 0.5372063328738433,
      "failures": 0,
      "speed": 50.644069005797974,
      "init_speed": 1207.2920439454304
    },
    {
      "sequence_name": "hand1",
      "sequence_length": 244,
      "overlap": 0.5202849758869696,
      "failures": 3,
      "speed": 57.85404725593394,
      "init_speed": 1814.0589569160995
    },
    {
      "sequence_name": "hand2",
      "sequence_length": 267,
      "overlap": 0.40487767292322413,
      "failures": 5,
      "speed": 60.67983376477021,
      "init_speed": 2020.8143881984438
    },
    {
      "sequence_name": "jogging",
      "sequence_length": 307,
      "overlap": 0.5802263795963186,
      "failures": 1,
      "speed": 55.496090080667315,
      "init_speed": 1791.1517105498833
    },
    {
      "sequence_name": "motocross",
      "sequence_length": 164,
      "overlap": 0.4724523431956882,
      "failures": 4,
      "speed": 30.536088054358707,
      "init_speed": 1133.2728921124208
    },
    {
      "sequence_name": "polarbear",
      "sequence_length": 371,
      "overlap": 0.5968052181149724,
      "failures": 0,
      "speed": 50.35486334463738,
      "init_speed": 1373.2491073880801
    },
    {
      "sequence_name": "skating",
      "sequence_length": 400,
      "overlap": 0.4907616940461013,
      "failures": 6,
      "speed": 39.867595896916114,
      "init_speed": 1461.1338398597313
    },
    {
      "sequence_name": "sphere",
      "sequence_length": 201,
      "overlap": 0.5287101561568126,
      "failures": 0,
      "speed": 41.36072164870171,
      "init_speed": 1369.6753869332967
    },
    {
      "sequence_name": "sunshade",
      "sequence_length": 172,
      "overlap": 0.5451387948258928,
      "failures": 0,
      "speed": 62.10260426187786,
      "init_speed": 1569.8587127158555
    },
    {
      "sequence_name": "surfing",
      "sequence_length": 282,
      "overlap": 0.586103953478775,
      "failures": 0,
      "speed": 68.52662840288778,
      "init_speed": 1786.99070764832
    },
    {
      "sequence_name": "torus",
      "sequence_length": 264,
      "overlap": 0.5824278276978302,
      "failures": 1,
      "speed": 61.18243479593786,
      "init_speed": 1814.3880976140795
    },
    {
      "sequence_name": "trellis",
      "sequence_length": 569,
      "overlap": 0.4332250202455271,
      "failures": 1,
      "speed": 50.56466139092584,
      "init_speed": 1692.3337282112032
    },
    {
      "sequence_name": "tunnel",
      "sequence_length": 731,
      "overlap": 0.39356581241889943,
      "failures": 12,
      "speed": 60.458259621982855,
      "init_speed": 1956.387605532062
    },
    {
      "sequence_name": "woman",
      "sequence_length": 597,
      "overlap": 0.593819939230754,
      "failures": 3,
      "speed": 57.44436895828844,
      "init_speed": 1852.366398073539
    }
  ],
  "average_overlap": 0.47995492092337905,
  "total_failures": 54,
  "average_speed": 51.964255359879054,
  "average_init_speed": 1548.5271536598946,
  "total_frames": 10213
}