{
  "tracker_name": "correlation-1.5ef-5sig-0.05al-0lmb",
  "results": [
    {
      "sequence_name": "ball",
      "sequence_length": 602,
      "overlap": 0.31108457925625804,
      "failures": 2,
      "speed": 647.9104234389126,
      "init_speed": 771.5850929760038
    },
    {
      "sequence_name": "basketball",
      "sequence_length": 725,
      "overlap": 0.5619990797934327,
      "failures": 4,
      "speed": 376.1649773640472,
      "init_speed": 516.0651067738706
    },
    {
      "sequence_name": "bicycle",
      "sequence_length": 271,
      "overlap": 0.48786308257596184,
      "failures": 7,
      "speed": 1423.9905489219868,
      "init_speed": 1255.6898446083817
    },
    {
      "sequence_name": "bolt",
      "sequence_length": 350,
      "overlap": 0.5079831729216389,
      "failures": 1,
      "speed": 568.9397068612154,
      "init_speed": 643.0868167202573
    },
    {
      "sequence_name": "car",
      "sequence_length": 252,
      "overlap": 0.38730035331443347,
      "failures": 0,
      "speed": 1720.5781142463866,
      "init_speed": 1449.4854326714017
    },
    {
      "sequence_name": "david",
      "sequence_length": 770,
      "overlap": 0.6395114877087839,
      "failures": 0,
      "speed": 312.3697149528989,
      "init_speed": 318.2584895452086
    },
    {
      "sequence_name": "diving",
      "sequence_length": 219,
      "overlap": 0.47018589191583743,
      "failures": 2,
      "speed": 364.10893656204206,
      "init_speed": 397.904370316334
    },
    {
      "sequence_name": "drunk",
      "sequence_length": 1210,
      "overlap": 0.39161368864174384,
      "failures": 1,
      "speed": 221.27672597635166,
      "init_speed": 185.32417831892437
    },
    {
      "sequence_name": "fernando",
      "sequence_length": 292,
      "overlap": 0.3711220784590284,
      "failures": 3,
      "speed": 158.84325801137325,
      "init_speed": 199.29317354449555
    },
    {
      "sequence_name": "fish1",
      "sequence_length": 436,
      "overlap": 0.28524783988325914,
      "failures": 11,
      "speed": 1079.9433580728512,
      "init_speed": 1123.2379205121963
    },
    {
      "sequence_name": "fish2",
      "sequence_length": 310,
      "overlap": 0.3323465655349935,
      "failures": 6,
      "speed": 527.5489375422641,
      "init_speed": 587.263102259285
    },
    {
      "sequence_name": "gymnastics",
      "sequence_length": 207,
      "overlap": 0.5159781926645044,
      "failures": 2,
      "speed": 306.07087740215655,
      "init_speed": 408.6525363700757
    },
    {
      "sequence_name": "hand1",
      "sequence_length": 244,
      "overlap": 0.3822536664964517,
      "failures": 6,
      "speed": 648.8326174055251,
      "init_speed": 718.6268068331143
    },
    {
      "sequence_name": "hand2",
      "sequence_length": 267,
      "overlap": 0.3957410010181377,
      "failures": 13,
      "speed": 617.1935777419899,
      "init_speed": 725.7082134618873
    },
    {
      "sequence_name": "jogging",
      "sequence_length": 307,
      "overlap": 0.3718494721515141,
      "failures": 1,
      "speed": 836.2630138256638,
      "init_speed": 672.3593088146306
    },
    {
      "sequence_name": "motocross",
      "sequence_length": 164,
      "overlap": 0.4075439849644435,
      "failures": 3,
      "speed": 131.52166849773096,
      "init_speed": 163.37333257092445
    },
    {
      "sequence_name": "polarbear",
      "sequence_length": 371,
      "overlap": 0.3738283304107346,
      "failures": 0,
      "speed": 1032.6049896252425,
      "init_speed": 691.6107614634484
    },
    {
      "sequence_name": "skating",
      "sequence_length": 400,
      "overlap": 0.40345915129450655,
      "failures": 1,
      "speed": 726.8267533181202,
      "init_speed": 539.5926075812761
    },
    {
      "sequence_name": "sphere",
      "sequence_length": 201,
      "overlap": 0.48313605122771286,
      "failures": 2,
      "speed": 511.0977054626014,
      "init_speed": 555.1443375277572
    },
    {
      "sequence_name": "sunshade",
      "sequence_length": 172,
      "overlap": 0.6315825114972383,
      "failures": 3,
      "speed": 1452.2653978707983,
      "init_speed": 1276.527844263603
    },
    {
      "sequence_name": "surfing",
      "sequence_length": 282,
      "overlap": 0.6425151329866489,
      "failures": 2,
      "speed": 1442.4225961290429,
      "init_speed": 1585.1209975694812
    },
    {
      "sequence_name": "torus",
      "sequence_length": 264,
      "overlap": 0.45032032724621934,
      "failures": 5,
      "speed": 908.9784721114971,
      "init_speed": 1019.6105087856439
    },
    {
      "sequence_name": "trellis",
      "sequence_length": 569,
      "overlap": 0.4212015558231724,
      "failures": 12,
      "speed": 617.6875603534692,
      "init_speed": 841.6527470250812
    },
    {
      "sequence_name": "tunnel",
      "sequence_length": 731,
      "overlap": 0.3124325320459402,
      "failures": 0,
      "speed": 508.6761997643112,
      "init_speed": 337.9748546708125
    },
    {
      "sequence_name": "woman",
      "sequence_length": 597,
      "overlap": 0.6728480833913097,
      "failures": 3,
      "speed": 545.165163144636,
      "init_speed": 447.14720085852264
    }
  ],
  "average_overlap": 0.44843791252895626,
  "total_failures": 90,
  "average_speed": 707.4912517841248,
  "average_init_speed": 697.2118234417046,
  "total_frames": 10213
}