{
  "tracker_name": "particle-NCVmm-125N-5q-0.01al-0.1dsig-16nbins",
  "results": [
    {
      "sequence_name": "ball",
      "sequence_length": 602,
      "overlap": 0.6069539404218959,
      "failures": 0,
      "speed": 61.02651133574548,
      "init_speed": 1271.7792191275596
    },
    {
      "sequence_name": "basketball",
      "sequence_length": 725,
      "overlap": 0.6362917144680464,
      "failures": 1,
      "speed": 46.57208794988307,
      "init_speed": 1297.2692482324705
    },
    {
      "sequence_name": "bicycle",
      "sequence_length": 271,
      "overlap": 0.3925096422607639,
      "failures": 1,
      "speed": 66.47213318884396,
      "init_speed": 1959.8236158745715
    },
    {
      "sequence_name": "bolt",
      "sequence_length": 350,
      "overlap": 0.5112142196978996,
      "failures": 3,
      "speed": 52.97362424441667,
      "init_speed": 1683.5725409318572
    },
    {
      "sequence_name": "car",
      "sequence_length": 252,
      "overlap": 0.35843900179265964,
      "failures": 0,
      "speed": 62.16505033013217,
      "init_speed": 1690.0456312320432
    },
    {
      "sequence_name": "david",
      "sequence_length": 770,
      "overlap": 0.5167158685639723,
      "failures": 3,
      "speed": 44.63141014506579,
      "init_speed": 1617.4686615446826
    },
    {
      "sequence_name": "diving",
      "sequence_length": 219,
      "overlap": 0.32652024218923076,
      "failures": 0,
      "speed": 47.722562724281076,
      "init_speed": 1538.4615384615386
    },
    {
      "sequence_name": "drunk",
      "sequence_length": 1210,
      "overlap": 0.33619255321776204,
      "failures": 0,
      "speed": 37.63479953183306,
      "init_speed": 1297.0168612191958
    },
    {
      "sequence_name": "fernando",
      "sequence_length": 292,
      "overlap": 0.37812711917296843,
      "failures": 1,
      "speed": 13.657571821428402,
      "init_speed": 843.0281571404485
    },
    {
      "sequence_name": "fish1",
      "sequence_length": 436,
      "overlap": 0.21831632786422422,
      "failures": 1,
      "speed": 67.91430805279285,
      "init_speed": 1472.4287712581904
    },
    {
      "sequence_name": "fish2",
      "sequence_length": 310,
      "overlap": 0.31365252908998115,
      "failures": 1,
      "speed": 44.5193034754198,
      "init_speed": 1272.5884448969202
    },
    {
      "sequence_name": "gymnastics",
      "sequence_length": 207,
      "overlap": 0.5465276135049084,
      "failures": 0,
      "speed": 50.86491737547049,
      "init_speed": 1396.8431345159938
    },
    {
      "sequence_name": "hand1",
      "sequence_length": 244,
      "overlap": 0.5086473838513328,
      "failures": 2,
      "speed": 58.13068467601261,
      "init_speed": 1768.659356207994
    },
    {
      "sequence_name": "hand2",
      "sequence_length": 267,
      "overlap": 0.44192764757244773,
      "failures": 8,
      "speed": 61.2229638740224,
      "init_speed": 2083.2368871811486
    },
    {
      "sequence_name": "jogging",
      "sequence_length": 307,
      "overlap": 0.5816172743795515,
      "failures": 1,
      "speed": 55.074437828584706,
      "init_speed": 1673.0801405387317
    },
    {
      "sequence_name": "motocross",
      "sequence_length": 164,
      "overlap": 0.4372253110882847,
      "failures": 4,
      "speed": 31.29359694946636,
      "init_speed": 1202.5590456491414
    },
    {
      "sequence_name": "polarbear",
      "sequence_length": 371,
      "overlap": 0.598474079337348,
      "failures": 0,
      "speed": 49.85653412748292,
      "init_speed": 1414.4271570014146
    },
    {
      "sequence_name": "skating",
      "sequence_length": 400,
      "overlap": 0.5066363403877151,
      "failures": 7,
      "speed": 40.23173609772082,
      "init_speed": 1536.8360388051099
    },
    {
      "sequence_name": "sphere",
      "sequence_length": 201,
      "overlap": 0.4456303361841903,
      "failures": 1,
      "speed": 44.59035676721811,
      "init_speed": 1502.1781583295779
    },
    {
      "sequence_name": "sunshade",
      "sequence_length": 172,
      "overlap": 0.4756633107339849,
      "failures": 0,
      "speed": 61.44045137870586,
      "init_speed": 1526.2515262515262
    },
    {
      "sequence_name": "surfing",
      "sequence_length": 282,
      "overlap": 0.616092890844962,
      "failures": 0,
      "speed": 68.03009757663042,
      "init_speed": 1781.5784785319793
    },
    {
      "sequence_name": "torus",
      "sequence_length": 264,
      "overlap": 0.544496373202566,
      "failures": 0,
      "speed": 59.947349877530336,
      "init_speed": 1641.4970453053186
    },
    {
      "sequence_name": "trellis",
      "sequence_length": 569,
      "overlap": 0.40809434467447614,
      "failures": 1,
      "speed": 50.53107940869693,
      "init_speed": 1696.928559307653
    },
    {
      "sequence_name": "tunnel",
      "sequence_length": 731,
      "overlap": 0.34563896313547043,
      "failures": 12,
      "speed": 59.66682916195227,
      "init_speed": 1984.5510334931153
    },
    {
      "sequence_name": "woman",
      "sequence_length": 597,
      "overlap": 0.5994361167467812,
      "failures": 4,
      "speed": 57.27256662098233,
      "init_speed": 1904.399162064369
    }
  ],
  "average_overlap": 0.466041645775337,
  "total_failures": 51,
  "average_speed": 51.73771858081275,
  "average_init_speed": 1562.2603365241023,
  "total_frames": 10213
}