{
  "tracker_name": "particle-NCVmm-150N-15q-0al-0.1dsig-32nbins",
  "results": [
    {
      "sequence_name": "ball",
      "sequence_length": 602,
      "overlap": 0.6204955284531928,
      "failures": 0,
      "speed": 28.321040464970913,
      "init_speed": 1117.9429849077696
    },
    {
      "sequence_name": "basketball",
      "sequence_length": 725,
      "overlap": 0.6224243082049333,
      "failures": 2,
      "speed": 23.751978855372283,
      "init_speed": 1212.3171421643901
    },
    {
      "sequence_name": "bicycle",
      "sequence_length": 271,
      "overlap": 0.4319036543857846,
      "failures": 5,
      "speed": 29.5686840695347,
      "init_speed": 1677.6834546857697
    },
    {
      "sequence_name": "bolt",
      "sequence_length": 350,
      "overlap": 0.454861333409473,
      "failures": 19,
      "speed": 27.892758776163856,
      "init_speed": 1512.6786354046415
    },
    {
      "sequence_name": "car",
      "sequence_length": 252,
      "overlap": 0.330024262683416,
      "failures": 0,
      "speed": 29.073971509700016,
      "init_speed": 1391.0140492418975
    },
    {
      "sequence_name": "david",
      "sequence_length": 770,
      "overlap": 0.5834241967733258,
      "failures": 3,
      "speed": 22.751931408605806,
      "init_speed": 1426.7879436418764
    },
    {
      "sequence_name": "diving",
      "sequence_length": 219,
      "overlap": 0.35124881338083275,
      "failures": 3,
      "speed": 22.464794492656868,
      "init_speed": 1403.6565252482717
    },
    {
      "sequence_name": "drunk",
      "sequence_length": 1210,
      "overlap": 0.35829934582646816,
      "failures": 0,
      "speed": 21.3586514998965,
      "init_speed": 1241.3108242303874
    },
    {
      "sequence_name": "fernando",
      "sequence_length": 292,
      "overlap": 0.40749011301405924,
      "failures": 0,
      "speed": 9.641994016931385,
      "init_speed": 732.4397568300006
    },
    {
      "sequence_name": "fish1",
      "sequence_length": 436,
      "overlap": 0.3292386168960483,
      "failures": 7,
      "speed": 29.061131773544385,
      "init_speed": 1520.3840055602614
    },
    {
      "sequence_name": "fish2",
      "sequence_length": 310,
      "overlap": 0.44917422489754233,
      "failures": 5,
      "speed": 25.847471060703477,
      "init_speed": 1460.387002555677
    },
    {
      "sequence_name": "gymnastics",
      "sequence_length": 207,
      "overlap": 0.5604165157135367,
      "failures": 1,
      "speed": 25.718170406823454,
      "init_speed": 1519.2950470981464
    },
    {
      "sequence_name": "hand1",
      "sequence_length": 244,
      "overlap": 0.5314252831903479,
      "failures": 2,
      "speed": 28.017955235380512,
      "init_speed": 1613.0766749112809
    },
    {
      "sequence_name": "hand2",
      "sequence_length": 267,
      "overlap": 0.43766633381125636,
      "failures": 3,
      "speed": 28.091230313376606,
      "init_speed": 1661.888736549088
    },
    {
      "sequence_name": "jogging",
      "sequence_length": 307,
      "overlap": 0.6336467631713089,
      "failures": 2,
      "speed": 27.582096333967655,
      "init_speed": 1667.0371193598576
    },
    {
      "sequence_name": "motocross",
      "sequence_length": 164,
      "overlap": 0.44541746665009835,
      "failures": 4,
      "speed": 17.676291658286853,
      "init_speed": 1175.1709873786635
    },
    {
      "sequence_name": "polarbear",
      "sequence_length": 371,
      "overlap": 0.6167987825137422,
      "failures": 0,
      "speed": 25.51911450461071,
      "init_speed": 1281.5583749839805
    },
    {
      "sequence_name": "skating",
      "sequence_length": 400,
      "overlap": 0.5288085479398686,
      "failures": 9,
      "speed": 22.837761520916622,
      "init_speed": 1321.7722322089455
    },
    {
      "sequence_name": "sphere",
      "sequence_length": 201,
      "overlap": 0.6423607822873457,
      "failures": 2,
      "speed": 21.90146971344479,
      "init_speed": 1372.3696248856359
    },
    {
      "sequence_name": "sunshade",
      "sequence_length": 172,
      "overlap": 0.49399314862899907,
      "failures": 0,
      "speed": 28.487343586679113,
      "init_speed": 1454.5454545454547
    },
    {
      "sequence_name": "surfing",
      "sequence_length": 282,
      "overlap": 0.4099011998619081,
      "failures": 2,
      "speed": 29.857646803783606,
      "init_speed": 1823.5973497051853
    },
    {
      "sequence_name": "torus",
      "sequence_length": 264,
      "overlap": 0.5535379227594037,
      "failures": 1,
      "speed": 28.491764033708805,
      "init_speed": 1470.4801117564887
    },
    {
      "sequence_name": "trellis",
      "sequence_length": 569,
      "overlap": 0.476515450874693,
      "failures": 2,
      "speed": 26.121506632627703,
      "init_speed": 1588.4782378481416
    },
    {
      "sequence_name": "tunnel",
      "sequence_length": 731,
      "overlap": 0.36030161118827003,
      "failures": 7,
      "speed": 27.951818936784786,
      "init_speed": 1624.9263705238357
    },
    {
      "sequence_name": "woman",
      "sequence_length": 597,
      "overlap": 0.5643953880024818,
      "failures": 8,
      "speed": 27.4514023330242,
      "init_speed": 1707.650273224044
    }
  ],
  "average_overlap": 0.4877507837807334,
  "total_failures": 87,
  "average_speed": 25.41759919765983,
  "average_init_speed": 1439.1379567779877,
  "total_frames": 10213
}