{
  "tracker_name": "particle-NCVmm-125N-10q-0.001al-0.1dsig-32nbins",
  "results": [
    {
      "sequence_name": "ball",
      "sequence_length": 602,
      "overlap": 0.6164296818903083,
      "failures": 0,
      "speed": 33.414849840131296,
      "init_speed": 1440.922190201729
    },
    {
      "sequence_name": "basketball",
      "sequence_length": 725,
      "overlap": 0.5995385524260182,
      "failures": 2,
      "speed": 28.020526047507754,
      "init_speed": 1211.044727918618
    },
    {
      "sequence_name": "bicycle",
      "sequence_length": 271,
      "overlap": 0.44900577610596365,
      "failures": 5,
      "speed": 35.47650533516357,
      "init_speed": 1811.1348571014594
    },
    {
      "sequence_name": "bolt",
      "sequence_length": 350,
      "overlap": 0.44204570128824977,
      "failures": 17,
      "speed": 32.258165265442635,
      "init_speed": 1466.5792470409606
    },
    {
      "sequence_name": "car",
      "sequence_length": 252,
      "overlap": 0.3447119058969305,
      "failures": 0,
      "speed": 34.37776202979184,
      "init_speed": 1300.221037576388
    },
    {
      "sequence_name": "david",
      "sequence_length": 770,
      "overlap": 0.5303534168642045,
      "failures": 3,
      "speed": 28.823915861605407,
      "init_speed": 1515.7256536566883
    },
    {
      "sequence_name": "diving",
      "sequence_length": 219,
      "overlap": 0.34618969135338923,
      "failures": 3,
      "speed": 26.760664945899897,
      "init_speed": 1403.3118158854898
    },
    {
      "sequence_name": "drunk",
      "sequence_length": 1210,
      "overlap": 0.38496926669363324,
      "failures": 0,
      "speed": 25.464637723743266,
      "init_speed": 1233.9585389930899
    },
    {
      "sequence_name": "fernando",
      "sequence_length": 292,
      "overlap": 0.41777929302013156,
      "failures": 0,
      "speed": 11.551652180195926,
      "init_speed": 771.7240314863406
    },
    {
      "sequence_name": "fish1",
      "sequence_length": 436,
      "overlap": 0.4069653581262715,
      "failures": 8,
      "speed": 33.995581743754485,
      "init_speed": 1627.372403832462
    },
    {
      "sequence_name": "fish2",
      "sequence_length": 310,
      "overlap": 0.40560381197066814,
      "failures": 5,
      "speed": 30.01939500499962,
      "init_speed": 1351.9359723123512
    },
    {
      "sequence_name": "gymnastics",
      "sequence_length": 207,
      "overlap": 0.5522289541346863,
      "failures": 0,
      "speed": 29.86639721693655,
      "init_speed": 1397.2334777141261
    },
    {
      "sequence_name": "hand1",
      "sequence_length": 244,
      "overlap": 0.4991149899311345,
      "failures": 2,
      "speed": 34.18634988011094,
      "init_speed": 1642.7554484722377
    },
    {
      "sequence_name": "hand2",
      "sequence_length": 267,
      "overlap": 0.4502735251819575,
      "failures": 6,
      "speed": 34.256448765907216,
      "init_speed": 1688.5372443072172
    },
    {
      "sequence_name": "jogging",
      "sequence_length": 307,
      "overlap": 0.5239143105557134,
      "failures": 0,
      "speed": 32.72260028491044,
      "init_speed": 1499.250374812594
    },
    {
      "sequence_name": "motocross",
      "sequence_length": 164,
      "overlap": 0.43295967273973757,
      "failures": 4,
      "speed": 21.282216664883695,
      "init_speed": 1008.7763542822555
    },
    {
      "sequence_name": "polarbear",
      "sequence_length": 371,
      "overlap": 0.6127852691716416,
      "failures": 0,
      "speed": 30.55876520975022,
      "init_speed": 1287.83000643915
    },
    {
      "sequence_name": "skating",
      "sequence_length": 400,
      "overlap": 0.4858735997365759,
      "failures": 8,
      "speed": 25.32204253732948,
      "init_speed": 1218.637022192734
    },
    {
      "sequence_name": "sphere",
      "sequence_length": 201,
      "overlap": 0.46643957058921287,
      "failures": 1,
      "speed": 28.133874800458344,
      "init_speed": 1395.5760240039076
    },
    {
      "sequence_name": "sunshade",
      "sequence_length": 172,
      "overlap": 0.5363012717799226,
      "failures": 0,
      "speed": 34.38102648672305,
      "init_speed": 1115.324559446799
    },
    {
      "sequence_name": "surfing",
      "sequence_length": 282,
      "overlap": 0.404102677834755,
      "failures": 1,
      "speed": 35.97542040222773,
      "init_speed": 1640.6890894175554
    },
    {
      "sequence_name": "torus",
      "sequence_length": 264,
      "overlap": 0.522128231375806,
      "failures": 1,
      "speed": 33.711810207902396,
      "init_speed": 1557.8750584203149
    },
    {
      "sequence_name": "trellis",
      "sequence_length": 569,
      "overlap": 0.47949990476960386,
      "failures": 2,
      "speed": 31.5223779636844,
      "init_speed": 1586.6299978844934
    },
    {
      "sequence_name": "tunnel",
      "sequence_length": 731,
      "overlap": 0.3604761065630089,
      "failures": 5,
      "speed": 33.19672763187328,
      "init_speed": 1646.045375984198
    },
    {
      "sequence_name": "woman",
      "sequence_length": 597,
      "overlap": 0.5454957751758297,
      "failures": 4,
      "speed": 32.57634029857358,
      "init_speed": 1650.6553101581326
    }
  ],
  "average_overlap": 0.47260745260701426,
  "total_failures": 77,
  "average_speed": 30.314242173180286,
  "average_init_speed": 1418.7898327816517,
  "total_frames": 10213
}